{"DataFrame1": {"block_address": ["eniw8y98cgbu00widgw"], "UID": ["sdser3e24g6yg"], "shareholdings": [10]}, "DataFrame2": {"time_stamp": ["2024-03-01", "2024-03-02"], "image": ["URL SOURCE 1", "URL SOURCE 2"], "title": ["Headline Title 1", "Headline Title 2"], "source_logo": ["URL SOURCE 1", "URL SOURCE 2"], "source_name": ["Headline Source 1", "Headline Source 2"], "author": ["Headline Author 1", "Headline Author 2"], "bod": ["Headline Body 1", "Headline Body 2"]}, "DataFrame3": {"time_stamp": ["2025-06-22", "2025-06-22", "2025-06-22"], "image": ["https://news.google.com/api/attachments/CC8iL0NnNVJTWEp3U1dORk1ETkdRekY2VFJEZkFoaUFCQ2dLTWdtQmNaYnNMQ2pnS3dJ=-w200-h112-p-df", "https://news.google.com/api/attachments/CC8iL0NnNUJUaTFXZDNSRlJHSktXWEJwVFJEVkFoaUFCQ2dLTWdrQmdJQUdVU01PZUFB=-w200-h112-p-df", "https://news.google.com/api/attachments/CC8iK0NnNXRaWEZsVFMxeE1tRjBlVWR6VFJDREFoakNBU2dCTWdZbFJKWnRJUWc=-w200-h112-p-df"], "article": ["Brasil prop\u00f5e plano global de financiamento clim\u00e1tico rumo \u00e0 COP30", "Agricultura sob aquecimento global: quanto a adapta\u00e7\u00e3o pode realmente proteger nossas colheitas?", "Financiamento clim\u00e1tico atual enxuga gelo, diz pesquisadora do Par\u00e1"], "source_logo": ["https://encrypted-tbn0.gstatic.com/faviconV2?url=https://www.tempo.com&client=NEWS_360&size=96&type=FAVICON&fallback_opts=TYPE,SIZE,URL", "https://encrypted-tbn0.gstatic.com/faviconV2?url=https://www.tempo.com&client=NEWS_360&size=96&type=FAVICON&fallback_opts=TYPE,SIZE,URL", "https://encrypted-tbn0.gstatic.com/faviconV2?url=https://www.uol.com.br&client=NEWS_360&size=96&type=FAVICON&fallback_opts=TYPE,SIZE,URL"], "source_name": ["Tempo.com", "Tempo.com", "UOL"], "author": ["", "", ""]}, "DataFrame4": {"index": [0], "record": [[1, 1, 1, 1, -1, -1, -1, -1, -1, 1, -1, 1, -1, -1, -1, -1, 1, -1, -1, -1, -1, -1, -1, 0, 0, 0, 0, 0, 0, 0, 0, 0, 0, 0, 0, 0, 0, 0, 0, 0, 0, 0, 0, 0, 0, 0, 0, 0, 0, 0, 0, 0]]}}