{"DataFrame1": {"block_address": ["eniw8y98cgbu00widgw"], "UID": ["sdser3e24g6yg"], "shareholdings": [10]}, "DataFrame2": {"time_stamp": ["2024-03-01", "2024-03-02"], "image": ["URL SOURCE 1", "URL SOURCE 2"], "title": ["Headline Title 1", "Headline Title 2"], "source_logo": ["URL SOURCE 1", "URL SOURCE 2"], "source_name": ["Headline Source 1", "Headline Source 2"], "author": ["Headline Author 1", "Headline Author 2"], "bod": ["Headline Body 1", "Headline Body 2"]}, "DataFrame3": {"time_stamp": ["2025-01-22", "2025-01-22", "2025-01-22"], "image": ["https://news.google.com/api/attachments/CC8iL0NnNW1iVmN5VHpKeFRuRklUVXh2VFJERUF4aW1CU2dLTWdrQkFJN2docW9HWlFJ=-w200-h112-p-df", "https://news.google.com/api/attachments/CC8iL0NnNXZhM0JWWkRZeFNqY3RZVEZyVFJEcUFoalBCaWdLTWdrQklJQ25OZU1rMUFB=-w200-h112-p-df", "https://news.google.com/api/attachments/CC8iK0NnNVRkbEZ3Y0c1aVpsY3pjRkE1VFJDYkF4anFCU2dLTWdZQkVJak1sUWc=-w200-h112-p-df"], "article": ["Action urged over climate change\u2019s impact on hydropower and wildlife", "Show Us the Money: Climate Finance and COP29", "Free webinar: Climate change \u2013 what will it cost your organisation and what can you do about it?"], "source_logo": ["https://lh3.googleusercontent.com/1LmK1Ipw0cxdlRJikPTdl9HoyobEPyItZrVBUzLtWu8y3omEl_xaHC4z8axEXWfvUr3Rxpnr=s0-h12", "https://encrypted-tbn1.gstatic.com/faviconV2?url=https://impakter.com&client=NEWS_360&size=96&type=FAVICON&fallback_opts=TYPE,SIZE,URL", "https://lh3.googleusercontent.com/ck_nfK9OSwMklheV7zwnuAttDzEnp4fNlShU2gk2P3O6xvxRVpvvcSPWwAaIgoyeFHcZ5XR9=s0-h12"], "source_name": ["Envirotec", "Impakter", "edie.net"], "author": ["", "", ""]}, "DataFrame4": {"index": [0], "record": [[1, 1, 0, 0, 0, 0, 0, 0, 0, 0, 0, 0, 0, 0, 0, 0, 0, 0, 0, 0, 0, 0, 0, 0, 0, 0, 0, 0, 0, 0, 0, 0, 0, 0, 0, 0, 0, 0, 0, 0, 0, 0, 0, 0, 0, 0, 0, 0, 0, 0, 0, 0]]}}